[{"time":"8:58","artist":"The Replacements","title":"Alex Chilton","id":131160},{"time":"8:53","artist":"Suzanne Vega","title":"Left Of Center","id":189647},{"time":"8:50","artist":"Tom Waits","title":"Hang On St. Christopher","id":130752},{"time":"8:46","artist":"Hoodoo Gurus","title":"What's My Scene","id":203222},{"time":"8:43","artist":"Love and Rockets","title":"No New Tale To Tell","id":156452},{"time":"8:37","artist":"Sisters Of Mercy","title":"This Corrosion","id":132255},{"time":"8:34","artist":"Prince","title":"If I Was Your Girlfriend","id":197491},{"time":"8:30","artist":"X","title":"See How We Are","id":138623},{"time":"8:27","artist":"INXS","title":"Need You Tonight","id":203221},{"time":"8:21","artist":"Depeche Mode","title":"Never Let Me Down Again","id":131772},{"time":"8:18","artist":"Public Enemy","title":"Timebomb","id":139374},{"time":"8:13","artist":"U2","title":"Bullet The Blue Sky","id":130867},{"time":"8:09","artist":"R.E.M.","title":"Finest Worksong","id":130981},{"time":"8:05","artist":"The Smiths","title":"Ask","id":207280},{"time":"8:00","artist":"The Stranglers","title":"Get A Grip On Yourself","id":130699}]