[{"time":"10:59","artist":"The BellRays","title":"You're Sorry Now","id":135532},{"time":"10:55","artist":"Ben Harper & the Blind Boys of Alabama","title":"There Will Be A Light","id":134604},{"time":"10:50","artist":"Paul Simon","title":"That's Me","id":149303},{"time":"10:46","artist":"The Subways","title":"Mary","id":142335},{"time":"10:43","artist":"This Mortal Coil","title":"Late Night","id":138779},{"time":"10:40","artist":"Semisonic","title":"Brand New Baby","id":130847},{"time":"10:37","artist":"Jurassic 5","title":"Get It Together","id":151327},{"time":"10:33","artist":"Starlight Mints","title":"Pumpkin","id":148614},{"time":"10:30","artist":"Son Volt","title":"Drown","id":133047},{"time":"10:28","artist":"Roy Orbison and the Teen Kings","title":"Ooby Dooby","id":136732},{"time":"10:21","artist":"The Cure","title":"A Forest","id":131179},{"time":"10:19","artist":"The Hidden Cameras","title":"Awoo","id":152475},{"time":"10:15","artist":"Mayday!","title":"4X4","id":150417},{"time":"10:11","artist":"Peter Gabriel","title":"Solsbury Hill","id":131451},{"time":"10:07","artist":"Alice Smith","title":"Desert Song","id":152124},{"time":"10:01","artist":"Rogue Wave","title":"Love's Lost Guarantee","id":141311}]