[{"time":"12:59","artist":"Air","title":"Kelly Watch The Stars","id":130993},{"time":"12:55","artist":"Metric","title":"Collect Call","id":196004},{"time":"12:52","artist":"Alexander","title":"Lets Win","id":212206},{"time":"12:46","artist":"Isaac Hayes","title":"Walk On By","id":139964},{"time":"12:43","artist":"G. Love","title":"Walk On","id":211599},{"time":"12:38","artist":"The Walkmen","title":"Blue As Your Blood","id":208694},{"time":"12:35","artist":"Desdamona","title":"Can't Be Me","id":150672},{"time":"12:30","artist":"Thievery Corporation","title":"The Heart's a Lonely Hunter","id":134416},{"time":"12:26","artist":"The Strokes","title":"Two Kinds Of Happiness","id":212403},{"time":"12:23","artist":"Tegan and Sara","title":"Walking With a Ghost","id":131008},{"time":"12:20","artist":"Lykke Li","title":"I Follow Rivers","id":212086},{"time":"12:15","artist":"The Black Keys","title":"Next Girl","id":205392},{"time":"12:11","artist":"Glasvegas","title":"It's My Own Cheating Heart That Makes Me Cry","id":194107},{"time":"12:07","artist":"Of Montreal","title":"Famine Affair","id":208776},{"time":"12:04","artist":"PJ Harvey","title":"The Last Living Rose","id":211485}]