[{"time":"5:55","artist":"Night Moves","title":"Horses","id":213364},{"time":"5:51","artist":"Doomtree","title":"Little Mercy","id":218354},{"time":"5:45","artist":"Matthew Sweet","title":"Divine Intervention","id":198468},{"time":"5:40","artist":"Kathleen Edwards","title":"Mint","id":219566},{"time":"5:36","artist":"Vampire Weekend","title":"Oxford Comma","id":161791},{"time":"5:33","artist":"Lee Fields","title":"You're The Kind of Girl","id":220769},{"time":"5:28","artist":"The Shins","title":"Simple Song","id":219443},{"time":"5:24","artist":"Free Energy","title":"Dream City","id":197122},{"time":"5:20","artist":"Edward Sharpe and The Magnetic Zeros","title":"Man On Fire","id":221297},{"time":"5:15","artist":"Bob Marley and The Wailers","title":"Concrete Jungle","id":210208},{"time":"5:12","artist":"Bon Iver","title":"Calgary","id":213903},{"time":"5:07","artist":"The Jayhawks","title":"I'm Gonna Make You Love Me","id":216764},{"time":"5:04","artist":"The Black Keys","title":"Gold On The Ceiling","id":218801},{"time":"5:00","artist":"Billy Bragg","title":"Greetings To The New Brunette","id":136230}]