[{"time":"6:56","artist":"Viva Voce","title":"Devotion","id":197177},{"time":"6:53","artist":"The National","title":"Brainy","id":159049},{"time":"6:48","artist":"Chuck Berry","title":"Thirty Days","id":131409},{"time":"6:44","artist":"Mos Def","title":"Casa Bey","id":197172},{"time":"6:41","artist":"The Mekons","title":"Hope and Anchor","id":186712},{"time":"6:36","artist":"The Avett Brothers","title":"I and Love and You","id":197822},{"time":"6:30","artist":"Ladyhawke","title":"Paris Is Burning","id":193052},{"time":"6:27","artist":"Phoenix","title":"1901","id":196009},{"time":"6:23","artist":"Joy Division","title":"Disorder","id":189912},{"time":"6:20","artist":"Nino Moschella","title":"Continue To Call","id":197174},{"time":"6:15","artist":"Free Energy","title":"Dream City","id":197122},{"time":"6:11","artist":"Clap Your Hands Say Yeah","title":"In This Home On Ice","id":140336},{"time":"6:08","artist":"Metric","title":"Help, I'm Alive","id":194747},{"time":"6:03","artist":"White Rabbits","title":"They Done Wrong / We Done Wrong","id":195634},{"time":"6:00","artist":"Nick Drake","title":"Pink Moon","id":132784}]