[{"time":"7:57","artist":"Ike and Tina Turner","title":"Proud Mary","id":146785},{"time":"7:52","artist":"Broken Social Scene","title":"7/4 (Shoreline)","id":141082},{"time":"7:46","artist":"The Black Keys","title":"Thickfreakness","id":179527},{"time":"7:43","artist":"The Lumineers","title":"Ho Hey","id":220559},{"time":"7:39","artist":"Brother Ali","title":"Shine On feat. Nikki Jean","id":220538},{"time":"7:34","artist":"Ladyhawke","title":"Magic","id":193053},{"time":"7:30","artist":"Bauhaus","title":"She's in Parties","id":132847},{"time":"7:24","artist":"Mos Def","title":"Blue Black Jack feat. Shuggie Otis","id":154821},{"time":"7:20","artist":"Gorillaz","title":"Do Ya Thing feat. James Murphy and Andre 3000","id":220703},{"time":"7:13","artist":"The Flying Burrito Brothers","title":"Sin City","id":210379},{"time":"7:10","artist":"Pernice Brothers","title":"Clear Spot","id":132834},{"time":"7:07","artist":"Big Star","title":"Back Of A Car","id":131919},{"time":"7:01","artist":"De La Soul","title":"A Rollerskating Jam Called Saturday","id":133953}]