[{"time":"9:57","artist":"Robyn Hitchcock & The Venus 3","title":"N.Y. Doll","id":152454},{"time":"9:49","artist":"The Poems","title":"Can You Come for Me","id":152852},{"time":"9:45","artist":"Vashti Bunyan","title":"Jog Along Bess","id":138823},{"time":"9:39","artist":"Dolorean","title":"Holding On","id":135609},{"time":"9:35","artist":"Lucinda Williams","title":"Are You Alright?","id":154814},{"time":"9:31","artist":"Someone Still Loves You Boris Yeltsin","title":"House Fire","id":151820},{"time":"9:26","artist":"John Vanderslice","title":"Exodus Damage","id":140240},{"time":"9:23","artist":"Bob Marley & The Wailers","title":"Get Up Stand Up","id":136561},{"time":"9:18","artist":"The Original Mark Edward","title":"Sleepy Memories","id":139515},{"time":"9:15","artist":"Sloan","title":"Can't You Figure It Out?","id":154540},{"time":"9:10","artist":"Rocky Votolato","title":"White Daisy Passing","id":145795},{"time":"9:08","artist":"Squeeze","title":"Is That Love","id":133115},{"time":"9:04","artist":"The Apples in Stereo","title":"Same Old Drag","id":154894},{"time":"9:00","artist":"Madeleine Peyroux","title":"I'm All Right","id":151702}]