[{"time":"11:58","artist":"Ian Dury","title":"Sex and Drugs and Rock and Roll","id":132052},{"time":"11:52","artist":"St. Germain","title":"Latin Note","id":134016},{"time":"11:49","artist":"Peter Gabriel","title":"Flume","id":203091},{"time":"11:44","artist":"Magazine","title":"Shot By Both Sides","id":132040},{"time":"11:40","artist":"Free Energy","title":"Bang Pop","id":203230},{"time":"11:36","artist":"Chairlift","title":"Bruises","id":193061},{"time":"11:33","artist":"The XX","title":"VCR","id":201154},{"time":"11:29","artist":"Cold War Kids","title":"Santa Ana Winds","id":203063},{"time":"11:26","artist":"Arctic Monkeys","title":"Crying Lightning","id":197827},{"time":"11:23","artist":"Johnny Cash","title":"Don't Take Your Guns To Town","id":130764},{"time":"11:19","artist":"Joanna Newsom","title":"'81","id":203646},{"time":"11:14","artist":"She and Him","title":"Thieves","id":204182},{"time":"11:10","artist":"Surfer Blood","title":"Floating Vibes","id":201569},{"time":"11:08","artist":"The Undertones","title":"Teenage Kicks","id":132048},{"time":"11:04","artist":"Sharon Jones and the Dap-Kings","title":"Give It Back","id":204382}]