[{"time":"6:56","artist":"The Rakes","title":"We Are All Animals","id":148455},{"time":"6:50","artist":"Curtis Mayfield","title":"Move On Up","id":139308},{"time":"6:47","artist":"Lemonheads","title":"Into Your Arms","id":139564},{"time":"6:45","artist":"The Lashes","title":"Nate's Song","id":146447},{"time":"6:38","artist":"Young MC","title":"Bust A Move","id":140146},{"time":"6:35","artist":"Beastie Boys","title":"Slow And Low","id":131135},{"time":"6:30","artist":"Air","title":"Surfing on a Rocket","id":134791},{"time":"6:26","artist":"Klee","title":"Two Questions","id":147489},{"time":"6:19","artist":"Elvis Costello & The Attractions","title":"Radio, Radio","id":135702},{"time":"6:15","artist":"Belle & Sebastian","title":"White Collar Boy","id":145185},{"time":"6:11","artist":"Guillemots","title":"Trains to Brazil","id":147008},{"time":"6:05","artist":"Soledad Brothers","title":"Crying Out Loud (Tears of Joy)","id":147048},{"time":"6:02","artist":"Eagles of Death Metal","title":"Shasta Beast","id":145649}]