[{"time":"1:59","artist":"Arcade Fire","title":"Half Light II (No Celebration)","id":206982},{"time":"1:56","artist":"Communist Daughter","title":"Ghosts","id":216603},{"time":"1:50","artist":"Travis","title":"The Fear","id":132798},{"time":"1:46","artist":"The Wombats","title":"1996","id":215609},{"time":"1:42","artist":"Matthew Sweet","title":"Scooby-Doo, Where Are You?","id":183803},{"time":"1:38","artist":"Etta James","title":"Sufferin' Until Suffrage"},{"time":"1:33","artist":"Her Space Holiday","title":"My Girlfriend's Boyfriend","id":193967},{"time":"1:29","artist":"Bon Iver","title":"Perth","id":214669},{"time":"1:26","artist":"Junior Kimbrough","title":"Done Got Old","id":133261},{"time":"1:22","artist":"Heartless Bastards","title":"Parted Ways","id":218444},{"time":"1:18","artist":"Kinky","title":"Again and So On","id":151829},{"time":"1:15","artist":"Beirut","title":"A Candle's Fire","id":219061},{"time":"1:11","artist":"Death Cab for Cutie","title":"You Are a Tourist","id":212626},{"time":"1:07","artist":"Mason Jennings","title":"Clutch","id":215678},{"time":"1:03","artist":"Sex Pistols","title":"Pretty Vacant","id":198490},{"time":"1:00","artist":"Jason Collett","title":"I'll Bring the Sun","id":145655}]