[{"time":"10:57","artist":"Booker T. Jones","title":"Green Onions","id":222035},{"time":"10:54","artist":"Eagles of Death Metal","title":"I Want You So Hard (Boy's Bad News)","id":148110},{"time":"10:51","artist":"Alt-J","title":"Tessellate","id":225844},{"time":"10:48","artist":"Twin Shadow","title":"Five Seconds","id":224753},{"time":"10:44","artist":"Phantogram","title":"Mouthful of Diamonds","id":203672},{"time":"10:40","artist":"Mates of State","title":"Fraud in the 80's","id":147889},{"time":"10:36","artist":"Matt and Kim","title":"Cameras","id":227100},{"time":"10:11","artist":"Rufus Wainwright","title":"Martha","id":207313},{"time":"10:06","artist":"DeVotchKa","title":"Queen of the Surface Streets","id":143340},{"time":"10:03","artist":"Electric Guest","title":"This Head I Hold","id":224343}]