[{"time":"10:57","artist":"Zion I & the Grouch","title":"Smack feat. DJ Platurn","id":154461},{"time":"10:52","artist":"Psapp","title":"Ev'rybody Wants To Be A Cat","id":149321},{"time":"10:50","artist":"Petula Clark","title":"Resist","id":136903},{"time":"10:45","artist":"The Frames","title":"Finally","id":134576},{"time":"10:41","artist":"Damien Rice","title":"9 Crimes","id":153068},{"time":"10:36","artist":"The M's","title":"Trucker Speed","id":145252},{"time":"10:33","artist":"Nic Armstrong & the Thieves","title":"Back In That Room","id":134843},{"time":"10:31","artist":"Chancellors","title":"So Fine","id":132727},{"time":"10:25","artist":"Dungen","title":"Gjort bort sig","id":139813},{"time":"10:19","artist":"Owusu & Hannibal","title":"Lonnie's Secret","id":153153},{"time":"10:13","artist":"The Dandy Warhols","title":"All The Money Or The Simple Life Honey","id":142313},{"time":"10:10","artist":"The Apples In Stereo","title":"Shine A Light","id":145717},{"time":"10:07","artist":"Lily Allen","title":"Smile","id":152173},{"time":"10:02","artist":"Strange Fruit Project","title":"You (The Only Ones)","id":152064}]