[{"time":"1:57","artist":"Pete Yorn and Scarlett Johansson","title":"Relator","id":199340},{"time":"1:54","artist":"The Breeders","title":"Do You Love Me Now","id":130401},{"time":"1:51","artist":"Brother Ali","title":"House Keys","id":199909},{"time":"1:48","artist":"Megafaun","title":"The Fade","id":198315},{"time":"1:44","artist":"Amazing Baby","title":"Headdress","id":197157},{"time":"1:38","artist":"Spanish Harlem Orchestra","title":"Sacala Bailar","id":159366},{"time":"1:33","artist":"The Avett Brothers","title":"Laundry Room","id":199740},{"time":"1:30","artist":"Laura Marling","title":"Rambling Man","id":190243},{"time":"1:27","artist":"Modest Mouse","title":"Autumn Beds","id":198197},{"time":"1:24","artist":"The Kinks","title":"Till The End Of The Day","id":150783},{"time":"1:21","artist":"Mike Doughty","title":"(You Should Be) Doubly (Gratified)","id":199466},{"time":"1:17","artist":"Jarvis Cocker","title":"Black Magic","id":157172},{"time":"1:14","artist":"The Big Pink","title":"Dominos","id":198336},{"time":"1:10","artist":"Fleet Foxes","title":"Quiet Houses","id":190683},{"time":"1:06","artist":"Elliot Brood","title":"Write It All Down For You","id":199315},{"time":"1:03","artist":"Aztec Camera","title":"Oblivious","id":132047}]