[{"time":"3:58","artist":"Steve Wynn & The Miracle 3","title":"No Tomorrow","id":148438},{"time":"3:53","artist":"Beck","title":"Black Tambourine (Remix)","id":139570},{"time":"3:50","artist":"Broadcast","title":"America's Boy","id":140758},{"time":"3:43","artist":"Klee","title":"This Is For Everyone","id":147487},{"time":"3:38","artist":"Clap Your Hands Say Yeah","title":"Upon This Tidal Wave Of Young Blood","id":140338},{"time":"3:32","artist":"The Wrens","title":"Happy","id":141036},{"time":"3:31","artist":"The Bleeding Hickeys","title":"Chinese Dragon","id":135622},{"time":"3:27","artist":"Chris Mills","title":"You Are My Favorite Song","id":141369},{"time":"3:24","artist":"Danielson","title":"Did I Step on Your Trumpet","id":147241},{"time":"3:20","artist":"Cursive","title":"Dispenser","id":140580},{"time":"3:16","artist":"the The","title":"Slow Emotion Replay","id":130692},{"time":"3:13","artist":"Rainer Maria","title":"Southpaw","id":148514},{"time":"3:13","artist":"Rainer Maria","title":"Southpaw","id":148514},{"time":"3:06","artist":"Calexico / Iron and Wine","title":"Sixteen, Maybe Less","id":144442},{"time":"3:01","artist":"The Concretes","title":"Grey Davis","id":147069}]