[{"time":"7:56","artist":"Kathleen Edwards","title":"Change The Sheets","id":216648},{"time":"7:52","artist":"Lee \"Scratch\" Perry","title":"War Dance","id":188939},{"time":"7:47","artist":"Now, Now","title":"Thread","id":220324},{"time":"7:44","artist":"Queen","title":"Crazy Little Thing Called Love","id":142300},{"time":"7:41","artist":"Fitz and the Tantrums","title":"Pickin' Up the Pieces","id":218359},{"time":"7:37","artist":"Delta Spirit","title":"Otherside","id":222704},{"time":"7:31","artist":"The Shins","title":"Simple Song","id":219443},{"time":"7:26","artist":"David Byrne and Brian Eno","title":"Strange Overtones","id":191162},{"time":"7:22","artist":"Art of Noise","title":"Close (To the Edit)","id":206489},{"time":"7:18","artist":"Kimbra","title":"Settle Down","id":217889},{"time":"7:13","artist":"Beady Eye","title":"The Roller","id":211208},{"time":"7:11","artist":"JD McPherson","title":"North Side Gal","id":220298},{"time":"7:08","artist":"The Jayhawks","title":"She Walks In So Many Ways","id":214823},{"time":"7:04","artist":"Of Monsters And Men","title":"Mountain Sound","id":221599}]