[{"time":"11:59","artist":"The Joggers","title":"Wicked Light Sleeper","id":140820},{"time":"11:57","artist":"Quasimoto","title":"Life is...","id":139139},{"time":"11:49","artist":"TV On The Radio","title":"Dreams","id":133392},{"time":"11:43","artist":"Okkervil River","title":"Last Love Song for Now","id":142282},{"time":"11:38","artist":"XTC","title":"King For A Day","id":133496},{"time":"11:31","artist":"Curtis Mayfield","title":"We Got To Have Peace (Eddie Baez Remix)","id":137582},{"time":"11:25","artist":"Di Dollari","title":"Tolex Remnants","id":135444},{"time":"11:21","artist":"James Blood Ulmer","title":"White Man's Jail","id":137722},{"time":"11:18","artist":"Laura Veirs","title":"Lake Swimming","id":140248},{"time":"11:14","artist":"Trampled by Turtles","title":"I'm a Target Too","id":136764},{"time":"11:10","artist":"Tullycraft","title":"Every Little Thing","id":136072},{"time":"11:07","artist":"Beth Orton","title":"Conceived","id":142053},{"time":"11:02","artist":"The Redwalls","title":"Robinson Crusoe","id":137064}]