[{"time":"12:57","artist":"Drive-By Truckers","title":"Used To Be A Cop","id":209614},{"time":"12:53","artist":"David Bazan","title":"Eating Paper","id":213873},{"time":"12:47","artist":"Lucinda Williams","title":"Seeing Black","id":212566},{"time":"12:44","artist":"The Pretenders","title":"Tattooed Love Boys","id":183681},{"time":"12:42","artist":"The Greenhornes","title":"Saying Goodbye","id":208862},{"time":"12:38","artist":"Cults","title":"Go Outside","id":214713},{"time":"12:33","artist":"Fleet Foxes","title":"Helplessness Blues","id":211100},{"time":"12:29","artist":"The Beatles","title":"Two Of Us","id":199268},{"time":"12:24","artist":"Iron and Wine","title":"Walking Far From Home","id":209500},{"time":"12:22","artist":"The Heavenly States","title":"Berlin Wall feat. Britt Daniel","id":214223},{"time":"12:19","artist":"Vampire Weekend","title":"Holiday","id":202467},{"time":"12:16","artist":"The Strokes","title":"Machu Picchu","id":212402},{"time":"12:11","artist":"Peter Bjorn And John","title":"Young Folks","id":155516},{"time":"12:06","artist":"The Rosebuds","title":"Woods","id":214416},{"time":"12:01","artist":"Talking Heads","title":"Take Me To The River","id":132278}]