[{"time":"5:56","artist":"Mavis Staples & Lucky Peterson","title":"Down By the Riverside"},{"time":"5:52","artist":"Dave Alvin","title":"Sign of  Judgment"},{"time":"5:49","artist":"Sam Cooke","title":"Summertime"},{"time":"5:45","artist":"Beach Boys","title":"Help Me Rhonda"},{"time":"5:41","artist":"Pat Donohue","title":"Weeping Willow Blues"},{"time":"5:37","artist":"Holly Cole","title":"Cry"},{"time":"5:31","artist":"Lucia Newell with Laura Caviani","title":"My Little Brown Book"},{"time":"5:30","artist":"Pink Martini","title":"Let’s Never Stop Falling In Love"},{"time":"5:22","artist":"Louden Wainwright III","title":"One Man Guy"},{"time":"5:19","artist":"Calexico","title":"Bisbee Blue"},{"time":"5:13","artist":"John Pizzarelli","title":"Splendid Splinter"},{"time":"5:12","artist":"Colorblind James Experience","title":"Oh Come Now"},{"time":"5:08","artist":"Doc Watson and John Herald","title":"Sing Song Kitty"},{"time":"5:03","artist":"The Duhks","title":"The Wagoner’s Lad"},{"time":"5:00","artist":"Rosanne Cash","title":"House on the Lake"}]