[{"time":"5:58","artist":"The La's","title":"There She Goes","id":189668},{"time":"5:54","artist":"Prince","title":"Laydown","id":206627},{"time":"5:50","artist":"Bright Eyes","title":"Shell Games","id":209871},{"time":"5:47","artist":"Wire","title":"Adapt","id":211008},{"time":"5:43","artist":"Trip Shakespeare","title":"Two Wheeler","id":131190},{"time":"5:40","artist":"Arcade Fire","title":"City With No Children","id":206983},{"time":"5:35","artist":"The Velvet Underground","title":"Rock and Roll","id":142344},{"time":"5:31","artist":"Cake","title":"Long Time","id":210903},{"time":"5:25","artist":"Led Zeppelin","title":"Misty Mountain Hop","id":139413},{"time":"5:20","artist":"Yeasayer","title":"O.N.E.","id":202770},{"time":"5:15","artist":"Junior Senior","title":"Can I Get Get Get","id":161295},{"time":"5:11","artist":"Tapes 'n Tapes","title":"Freak Out","id":208671},{"time":"5:08","artist":"Richard Hell and The Voidoids","title":"Blank Generation","id":132003},{"time":"5:05","artist":"Kings of Convenience","title":"Boat Behind","id":200171},{"time":"5:01","artist":"Grouplove","title":"Colours","id":210661}]