[{"time":"9:57","artist":"TV On The Radio","title":"Mercy","id":233941},{"time":"9:52","artist":"The Little Mermaid","title":"Under The Sea","id":202439},{"time":"9:49","artist":"The Hopefuls","title":"Drain the Sea","id":133602},{"time":"9:45","artist":"Modest Mouse","title":"Ocean Breathes Salty","id":132354},{"time":"9:38","artist":"Led Zeppelin","title":"The Ocean","id":139389},{"time":"9:35","artist":"Billie Holiday","title":"How Deep Is The Ocean","id":130821},{"time":"9:34","artist":"Ween","title":"Ocean Man"},{"time":"9:26","artist":"Preservation Hall Jazz Band","title":"Dear Lord (Give Me The Strength)","id":232011},{"time":"9:19","artist":"The Sugarcubes","title":"Birthday","id":132196},{"time":"9:16","artist":"Edward Sharpe and The Magnetic Zeros","title":"Better Days","id":232012},{"time":"9:04","artist":"The Wrens","title":"This Boy Is Exhausted","id":141038},{"time":"9:00","artist":"Laura Marling","title":"Where Can I Go","id":230110}]