[{"time":"11:59","artist":"The English Beat","title":"Twist And Crawl","id":139787},{"time":"11:53","artist":"Doves","title":"Jetstream","id":194536},{"time":"11:51","artist":"The Starfolk","title":"Come and Play","id":233908},{"time":"11:46","artist":"Depeche Mode","title":"Soothe My Soul","id":230114},{"time":"11:43","artist":"Lorde","title":"Royals","id":231311},{"time":"11:39","artist":"Edwyn Collins","title":"A Girl Like You","id":131722},{"time":"11:36","artist":"NONONO","title":"Pumpin Blood","id":233716},{"time":"11:31","artist":"Laura Marling","title":"Where Can I Go","id":230110},{"time":"11:28","artist":"Grizzly Bear","title":"Yet Again","id":224600},{"time":"11:23","artist":"Billy Paul","title":"Me And Mrs. Jones","id":140311},{"time":"11:19","artist":"Volcano Choir","title":"Byegone","id":232690},{"time":"11:16","artist":"New Politics","title":"Harlem","id":232074},{"time":"11:12","artist":"Outkast","title":"The Way You Move (Club Mix)","id":221442},{"time":"11:09","artist":"Flume","title":"Holdin On","id":229132},{"time":"11:05","artist":"The Pretenders","title":"Talk of the Town","id":133054}]