[{"time":"12:55","artist":"The Walkmen","title":"Blue As Your Blood","id":208694},{"time":"12:53","artist":"Ratatat","title":"Neckbrace","id":205936},{"time":"12:49","artist":"U2","title":"Wire","id":201086},{"time":"12:44","artist":"Jonquil","title":"I Know I Don't Know","id":209707},{"time":"12:39","artist":"The Beach Boys","title":"Good Vibrations","id":143142},{"time":"12:36","artist":"Jeremy Messersmith","title":"A Girl, a Boy, and a Graveyard","id":208497},{"time":"12:34","artist":"Cloud Cult","title":"Fairy Tale","id":134281},{"time":"12:28","artist":"Warpaint","title":"Undertow","id":208771},{"time":"12:24","artist":"Wilco","title":"You and I","id":197433},{"time":"12:20","artist":"The National","title":"Bloodbuzz Ohio","id":209619},{"time":"12:15","artist":"Spoon","title":"The Mystery Zone","id":203238},{"time":"12:12","artist":"Apex Manor","title":"Under the Gun","id":209495},{"time":"12:07","artist":"R.E.M.","title":"Crush With Eyeliner","id":130962}]