[{"time":"2:56","artist":"Alt-J","title":"Matilda","id":226744},{"time":"2:51","artist":"Led Zeppelin","title":"Rock and Roll","id":139416},{"time":"2:47","artist":"The Suburbs","title":"Turn The Radio On","id":233350},{"time":"2:43","artist":"Phoenix","title":"Entertainment","id":229191},{"time":"2:39","artist":"The Ericksons","title":"Animal","id":233674},{"time":"2:34","artist":"Rogue Valley","title":"Rockaway","id":210271},{"time":"2:30","artist":"Superchunk","title":"Trees of Barcelona","id":234391},{"time":"2:27","artist":"Iron and Wine","title":"Tree By The River","id":209699},{"time":"2:24","artist":"Mason Jennings","title":"Lonely Street","id":235529},{"time":"2:19","artist":"Queen and David Bowie","title":"Under Pressure","id":130726},{"time":"2:16","artist":"Dan Croll","title":"From Nowhere","id":225838},{"time":"2:09","artist":"Clap Your Hands Say Yeah","title":"The Skin of My Yellow Country Teeth","id":140333},{"time":"2:06","artist":"Willy Mason","title":"Talk Me Down","id":229230},{"time":"2:02","artist":"The Modern Lovers","title":"Roadrunner","id":205436}]