[{"time":"12:58","artist":"David Bowie","title":"The Jean Genie","id":130718},{"time":"12:53","artist":"Johnny Marr","title":"The Messenger","id":227141},{"time":"12:49","artist":"First Aid Kit","title":"My Silver Lining","id":240294},{"time":"12:46","artist":"De La Soul","title":"Vocabulary Spills","id":240122},{"time":"12:42","artist":"Tears for Fears","title":"Change","id":189908},{"time":"12:38","artist":"Man Man","title":"Head On","id":233432},{"time":"12:35","artist":"Caroline Smith","title":"Bloodstyle","id":236870},{"time":"12:30","artist":"The Afghan Whigs","title":"The Lottery","id":240997},{"time":"12:27","artist":"The Byrds","title":"I Knew I'd Want To","id":210075},{"time":"12:24","artist":"HAIM","title":"Don't Save Me","id":226504},{"time":"12:21","artist":"St. Paul and the Broken Bones","title":"Call Me","id":238862},{"time":"12:14","artist":"Yeasayer","title":"O.N.E.","id":202770},{"time":"12:10","artist":"Conor Oberst","title":"Hundreds of Ways","id":239163},{"time":"12:08","artist":"Elastica","title":"Connection","id":136190},{"time":"12:03","artist":"Avey Tare's Slasher Flicks","title":"Little Fang","id":239575}]