[{"time":"7:57","artist":"Nanci Griffith","title":"Anyone Can Be Someone's Fool"},{"time":"7:57","artist":"Leandra Peak","title":"Wash My Eyes"},{"time":"7:51","artist":"Peter Mayer","title":"Magical World"},{"time":"7:44","artist":"John Prine","title":"The Other Side of Town"},{"time":"7:38","artist":"John Williams and Dean Magraw","title":"The Gypsy Queen"},{"time":"7:37","artist":"Lou Rawls","title":"Love is a Hurtin' Thing"},{"time":"7:30","artist":"Mary Chapin Carpenter","title":"One Small Heart"},{"time":"7:28","artist":"Leonard Cohen","title":"Anthem"},{"time":"7:13","artist":"Willie Nelson","title":"Valentine"},{"time":"7:11","artist":"Peter Sellers","title":"She Loves You"},{"time":"7:07","artist":"Flogging Molly","title":"The Worst Day Since Yesterday"},{"time":"7:05","artist":"T.C. Higgins","title":"Cornbread Kisses"}]