[{"time":"4:59","artist":"The Black Lips","title":"Cold Hands","id":178710},{"time":"4:52","artist":"Grizzly Bear","title":"Colorado","id":152419},{"time":"4:49","artist":"The Hidden Cameras","title":"Awoo","id":152475},{"time":"4:46","artist":"The Hopefuls","title":"Drain the Sea","id":133602},{"time":"4:42","artist":"Manu Chao","title":"Rainin in Paradise","id":161156},{"time":"4:36","artist":"Built to Spill","title":"Liar","id":147923},{"time":"4:31","artist":"The Fall","title":"What You Need","id":148445},{"time":"4:28","artist":"Badly Drawn Boy","title":"Born In The U.K.","id":179432},{"time":"4:23","artist":"Beck","title":"Girl","id":136092},{"time":"4:20","artist":"Rilo Kiley","title":"The Moneymaker","id":161193},{"time":"4:17","artist":"Jim Noir","title":"Eanie Meany","id":151407},{"time":"4:14","artist":"Shout Out Louds","title":"Comeback","id":135942},{"time":"4:11","artist":"The New Pornographers","title":"All The Things That Go To Make Heaven And Earth","id":161876},{"time":"4:00","artist":"Smashing Pumpkins","title":"United States","id":160499}]