[{"time":"4:56","artist":"Beach House","title":"Zebra","id":203662},{"time":"4:52","artist":"Spiritualized","title":"Electricity","id":138862},{"time":"4:48","artist":"Ray LaMontagne and The Pariah Dogs","title":"New York City's Killing Me","id":207322},{"time":"4:44","artist":"Walt Mink","title":"Betty","id":137255},{"time":"4:42","artist":"The Chemical Brothers","title":"Another World","id":206471},{"time":"4:40","artist":"Junior Senior","title":"Dynamite","id":139975},{"time":"4:37","artist":"Best Coast","title":"Boyfriend","id":207159},{"time":"4:34","artist":"The Alarmists","title":"Car Crashing","id":196902},{"time":"4:31","artist":"The Gaslight Anthem","title":"The Diamond Church Street Choir","id":206243},{"time":"4:26","artist":"Jimi Hendrix","title":"Are You Experienced","id":205340},{"time":"4:24","artist":"Junip","title":"Far Away","id":206242},{"time":"4:21","artist":"Tapes 'n Tapes","title":"Cowbell","id":141605},{"time":"4:16","artist":"The National","title":"Terrible Love","id":205469},{"time":"4:12","artist":"Janelle Monae","title":"Tightrope feat. Big Boi","id":204356},{"time":"4:09","artist":"Sleigh Bells","title":"Crown On The Ground","id":206165},{"time":"4:05","artist":"Joy Division","title":"Transmission","id":134889},{"time":"4:01","artist":"Mumford and Sons","title":"Winter Winds","id":203218}]