[{"time":"10:57","artist":"Caroline Smith and the Good Night Sleeps","title":"Cry Baby Cry","id":226908},{"time":"10:52","artist":"Wilco","title":"Heavy Metal Drummer","id":159032},{"time":"10:48","artist":"Macklemore and Ryan Lewis","title":"Same Love feat. Mary Lambert","id":226351},{"time":"10:42","artist":"Goldfrapp","title":"Fly Me Away","id":145778},{"time":"10:38","artist":"Gold Fields","title":"Dark Again","id":226313},{"time":"10:33","artist":"Peter Wolf Crier","title":"You're So High","id":200103},{"time":"10:30","artist":"Cat Power","title":"3,6,9","id":225212},{"time":"10:25","artist":"Incredible Bongo Band","title":"Apache","id":154414},{"time":"10:22","artist":"Frank Ocean","title":"Thinkin Bout You","id":226428},{"time":"10:16","artist":"Phoenix","title":"Lisztomania","id":196919},{"time":"10:12","artist":"Passion Pit","title":"Carried Away","id":224252},{"time":"10:09","artist":"Jack White","title":"Freedom At 21","id":224258},{"time":"10:05","artist":"Milo Greene","title":"1957","id":224491},{"time":"10:01","artist":"Radiohead","title":"The Bends","id":130496}]