[{"time":"4:57","artist":"Soul Asylum","title":"Tied To The Tracks","id":131211},{"time":"4:54","artist":"Thunderbirds Are Now!","title":"Harpoons Of Love (Aquati","id":135905},{"time":"4:49","artist":"Magazine","title":"Shot By Both Sides","id":132040},{"time":"4:41","artist":"David Bowie","title":"The Jean Genie","id":130718},{"time":"4:39","artist":"The Elegants","title":"Little Star","id":132675},{"time":"4:35","artist":"Belly","title":"Gepetto","id":130910},{"time":"4:29","artist":"Small faces","title":"Itchykoo Park"},{"time":"4:27","artist":"Gang Starr","title":"Words I Manifest","id":134076},{"time":"4:23","artist":"Jamie Cullum","title":"Get Your Way","id":141135},{"time":"4:15","artist":"Hot Hot Heat","title":"Middle of Nowhere","id":135937},{"time":"4:11","artist":"The Wrens","title":"This Boy Is Exhausted","id":141038},{"time":"4:07","artist":"Mark Mallman","title":"Ghost to Ghost","id":131838},{"time":"4:02","artist":"Thievery Corporation","title":"The Heart's a Lonely Hunter","id":134416}]