[{"time":"5:59","artist":"Blondie","title":"Hanging On The Telephone","id":130412},{"time":"5:55","artist":"The Helio Sequence","title":"October","id":223982},{"time":"5:47","artist":"Atoms For Peace","title":"Default","id":225397},{"time":"5:43","artist":"Teenage Fanclub","title":"Star Sign","id":130533},{"time":"5:39","artist":"Tegan and Sara","title":"Closer","id":225722},{"time":"5:35","artist":"Bahamas","title":"Caught Me Thinking","id":218888},{"time":"5:31","artist":"The Kills","title":"No Wow","id":136109},{"time":"5:29","artist":"The Runaways","title":"Cherry Bomb","id":132006},{"time":"5:25","artist":"Ben Folds Five","title":"Do It Anyway","id":224742},{"time":"5:20","artist":"Blur","title":"The Puritan","id":223798},{"time":"5:15","artist":"Florence and the Machine","title":"No Light, No Light","id":218048},{"time":"5:11","artist":"George Harrison","title":"All Things Must Pass","id":139490},{"time":"5:07","artist":"The Avett Brothers","title":"Live and Die","id":223721},{"time":"5:02","artist":"LCD Soundsystem","title":"Disco Infiltrator","id":134854}]