[{"time":"3:59","artist":"Cloud Cult","title":"Please Remain Calm","id":157644},{"time":"3:55","artist":"Laura Marling","title":"Where Can I Go","id":230110},{"time":"3:52","artist":"The Pines","title":"Highwayman feat. Dave Simonett and Erik Koskinen","id":236783},{"time":"3:47","artist":"Broken Bells","title":"Holding On For Life","id":236584},{"time":"3:42","artist":"Wilco","title":"Via Chicago","id":195587},{"time":"3:38","artist":"Walk The Moon","title":"Tightrope","id":226161},{"time":"3:34","artist":"HAIM","title":"Don't Save Me","id":226504},{"time":"3:28","artist":"Carroll","title":"She Said She Said","id":237065},{"time":"3:26","artist":"Led Zeppelin","title":"Immigrant Song","id":139388},{"time":"3:22","artist":"Queens of the Stone Age","title":"My God Is The Sun","id":230551},{"time":"3:17","artist":"Pearl Jam","title":"Sirens","id":235333},{"time":"3:14","artist":"Otis Redding","title":"Respect","id":131090},{"time":"3:11","artist":"Caroline Smith","title":"Magazine","id":235111},{"time":"3:07","artist":"LCD Soundsystem","title":"Daft Punk Is Playing At My House","id":134939},{"time":"3:03","artist":"Mazzy Star","title":"California","id":235332},{"time":"3:00","artist":"Violent Femmes","title":"Blister In The Sun","id":131692}]