[{"time":"8:55","artist":"Bob Marley and the Wailers","title":"Bend Down Low"},{"time":"8:52","artist":"Extraordinary Rendition","title":"Rupa & the April Fishes"},{"time":"8:47","artist":"Robin and Linda Williams","title":"Seventeen Years Old"},{"time":"8:44","artist":"Ingrid Michaelson","title":"The Hat"},{"time":"8:34","artist":"Roma Di Luna","title":"The Romance of Wolves"},{"time":"8:30","artist":"Richard Julian","title":"Can’t Go Back"},{"time":"8:26","artist":"Kieran Kane, Kevin Welch & Fats Kaplan","title":"Mr. Bones"},{"time":"8:23","artist":"Laurel Aitken","title":"Boogie In My Bones"},{"time":"8:14","artist":"Martin Sexton","title":"Happy"},{"time":"8:10","artist":"Harry Manx and Kevin Breit","title":"Bottom of the Hill"},{"time":"8:08","artist":"Connie Evingson","title":"Lover Come Back to Me"},{"time":"8:02","artist":"Jim Kweskin","title":"Side By Side"}]