[{"time":"1:54","artist":"Breakestra","title":"Burgundy Blues","id":141252},{"time":"1:49","artist":"Morcheeba","title":"Bullet Proof","id":133857},{"time":"1:45","artist":"Sinead O'Connor","title":"Throw Down Your Arms","id":141027},{"time":"1:42","artist":"Bob Marley & The Wailers","title":"Three Little Birds","id":130676},{"time":"1:38","artist":"The Most Serene Republic","title":"Content Was Always My Favorite Color","id":141519},{"time":"1:34","artist":"Idlewild","title":"Love Steals Us From Loneliness","id":139837},{"time":"1:32","artist":"Toshi Reagon","title":"Soul-N-Deep","id":140372},{"time":"1:28","artist":"The Suburbs","title":"Goggles","id":131197},{"time":"1:23","artist":"Ash","title":"Orpheus","id":137134},{"time":"1:21","artist":"Go Go Go Airheart","title":"So Good","id":141775},{"time":"1:17","artist":"The Futureheads","title":"Decent Days and Nights","id":143397},{"time":"1:11","artist":"John Prine","title":"Taking A Walk","id":136441},{"time":"1:09","artist":"Ryan Adams & The Cardinals","title":"The Hardest Part","id":141727},{"time":"1:03","artist":"Cloud Cult","title":"Transistor Radio","id":136626}]