[{"time":"1:56","artist":"Ben Howard","title":"The Wolves","id":221068},{"time":"1:52","artist":"Mayer Hawthorne","title":"No Strings","id":219688},{"time":"1:49","artist":"Talking Heads","title":"Don't Worry About The Government","id":151755},{"time":"1:45","artist":"Black Box Revelation","title":"High On A Wire","id":217203},{"time":"1:40","artist":"Silversun Pickups","title":"Bloody Mary (Nerve Endings)","id":221424},{"time":"1:36","artist":"Florence and the Machine","title":"Shake It Out","id":217225},{"time":"1:32","artist":"The Band","title":"Life Is A Carnival","id":195466},{"time":"1:28","artist":"Dessa","title":"Dixon's Girl","id":216276},{"time":"1:25","artist":"Bon Iver","title":"Perth","id":214669},{"time":"1:19","artist":"Santigold","title":"Disparate Youth","id":220775},{"time":"1:16","artist":"Beck","title":"Girl","id":136092},{"time":"1:11","artist":"Lucero","title":"On My Way Downtown","id":220611},{"time":"1:01","artist":"Prince","title":"Purple Rain","id":197427}]