[{"time":"1:59","artist":"Yukon Blonde","title":"Stairway","id":220571},{"time":"1:54","artist":"Afghan Whigs","title":"Gentlemen","id":132505},{"time":"1:47","artist":"Doomtree","title":"Little Mercy","id":218354},{"time":"1:45","artist":"Mount Moriah","title":"Lament","id":213872},{"time":"1:40","artist":"Patrick Watson","title":"Into Giants","id":220837},{"time":"1:35","artist":"The Kills","title":"Satellite","id":211215},{"time":"1:33","artist":"Zeus","title":"Are You Gonna Waste My Time?","id":221042},{"time":"1:30","artist":"13th Floor Elevators","title":"You're Gonna Miss Me","id":134981},{"time":"1:28","artist":"Howler","title":"Pythagorean Fearem","id":220881},{"time":"1:23","artist":"The Postal Service","title":"Such Great Heights","id":132998},{"time":"1:18","artist":"Polica","title":"Wandering Star","id":219514},{"time":"1:15","artist":"The Jayhawks","title":"She Walks In So Many Ways","id":214823},{"time":"1:11","artist":"Brendan Benson","title":"Bad For Me","id":219980},{"time":"1:06","artist":"Iggy Pop","title":"Lust For Life","id":131801},{"time":"1:02","artist":"Grouplove","title":"Tongue Tied","id":216740}]