[{"time":"2:54","artist":"Drive-By Truckers","title":"Used To Be A Cop","id":209614},{"time":"2:51","artist":"The Decemberists","title":"Down By The Water","id":208835},{"time":"2:45","artist":"The New Pornographers","title":"Sing Me Spanish Techno","id":140699},{"time":"2:41","artist":"The Wombats","title":"Techno Fan","id":213874},{"time":"2:40","artist":"Natalie Cole (She's A Differnt Lady)","title":"Sophisticated Lady"},{"time":"2:35","artist":"Teddybears","title":"Cardiac Arrest feat. Robyn","id":214017},{"time":"2:30","artist":"Fleet Foxes","title":"Montezuma","id":213425},{"time":"2:27","artist":"The XX","title":"VCR","id":201154},{"time":"2:23","artist":"TV On The Radio","title":"Second Song","id":213194},{"time":"2:14","artist":"The Time","title":"777-9311","id":154917},{"time":"2:11","artist":"Gorillaz","title":"Rhinestone Eyes","id":206596},{"time":"2:08","artist":"The Strokes","title":"Under Control","id":144224},{"time":"2:05","artist":"Arctic Monkeys","title":"Don't Sit Down 'Cause I've Moved Your Chair","id":213077}]