[{"time":"5:58","artist":"The Waterboys","title":"Don't Bang the Drum","id":139346},{"time":"5:54","artist":"The Kills","title":"Satellite","id":211215},{"time":"5:51","artist":"Ryan Adams","title":"Love Is Hell","id":134679},{"time":"5:48","artist":"Alexander","title":"Lets Win!","id":212094},{"time":"5:44","artist":"Polara","title":"Time Slipping Away","id":136069},{"time":"5:41","artist":"The Decemberists","title":"Rox In The Box","id":210745},{"time":"5:38","artist":"The Beatles","title":"Ticket To Ride","id":199174},{"time":"5:34","artist":"Beady Eye","title":"The Roller","id":211208},{"time":"5:29","artist":"Foo Fighters","title":"Times Like These","id":201192},{"time":"5:26","artist":"Iron and Wine","title":"Tree By The River","id":209699},{"time":"5:22","artist":"Matt and Kim","title":"Cameras","id":207721},{"time":"5:19","artist":"Buffalo Tom","title":"Guilty Girls","id":212553},{"time":"5:15","artist":"David Bowie","title":"The Man Who Sold The World","id":139919},{"time":"5:11","artist":"Local Natives","title":"Airplanes","id":205465},{"time":"5:08","artist":"Cold War Kids","title":"Every Valley Is Not A Lake","id":194033},{"time":"5:04","artist":"Tapes 'n Tapes","title":"Badaboom","id":210240}]