[{"time":"8:58","artist":"Wilco","title":"A Shot In The Arm","id":195584},{"time":"8:56","artist":"The Starfolk","title":"Come and Play","id":233908},{"time":"8:50","artist":"HAIM","title":"The Wire","id":234210},{"time":"8:44","artist":"Pulp","title":"After You","id":228105},{"time":"8:41","artist":"Dr. Dog","title":"Broken Heart","id":235418},{"time":"8:35","artist":"Volcano Choir","title":"Acetate","id":235106},{"time":"8:32","artist":"Toots and The Maytals","title":"Do The Reggay","id":200792},{"time":"8:28","artist":"Grizzly Bear","title":"Yet Again","id":224600},{"time":"8:24","artist":"Alt-J","title":"Matilda","id":226744},{"time":"8:19","artist":"Fire In The Northern Firs","title":"Chatrooms","id":224994},{"time":"8:16","artist":"TV On The Radio","title":"Mercy","id":233941},{"time":"8:11","artist":"The Head and the Heart","title":"Lost in My Mind","id":211617},{"time":"8:07","artist":"Bear's Den","title":"Agape","id":234429},{"time":"8:03","artist":"Sugar","title":"Helpless","id":132771},{"time":"8:01","artist":"Bad Religion","title":"Land of Endless Greed","id":228481}]