[{"time":"12:58","artist":"Dot Allison","title":"Colour Me","id":130919},{"time":"12:50","artist":"The Smashing Pumpkins","title":"Eye","id":130574},{"time":"12:45","artist":"Nirvana","title":"Smells Like Teen Spirit","id":200620},{"time":"12:41","artist":"Beastie Boys","title":"Root Down","id":198760},{"time":"12:36","artist":"Guided By Voices","title":"Cut-Out Witch"},{"time":"12:33","artist":"Pearl Jam","title":"Animal","id":200699},{"time":"12:29","artist":"Temple of the Dog","title":"Hunger Strike","id":200602},{"time":"12:24","artist":"Red Hot Chili Peppers","title":"Taste the Pain","id":134025},{"time":"12:20","artist":"Soul Coughing","title":"Super Bon Bon Propellerheads","id":130566},{"time":"12:15","artist":"Papas Fritas","title":"We've Got All Night","id":146572},{"time":"12:12","artist":"Jesus Jones","title":"Right Here Right Now","id":232800},{"time":"12:09","artist":"Stereolab","title":"Ping Pong","id":131831},{"time":"12:06","artist":"R.E.M.","title":"Daysleeper","id":140015},{"time":"12:00","artist":"Lauryn Hill","title":"Everything Is Everything","id":133845}]