[{"time":"6:52","artist":"The Biddies in studio","title":"Quiet Way"},{"time":"6:48","artist":"The Kinks","title":"Alcohol"},{"time":"6:44","artist":"Jimmy Lafave","title":"Bohemian Cowboy Blues"},{"time":"6:37","artist":"George Maurer Group","title":"I Got Rhythm"},{"time":"6:32","artist":"Nickel Creek","title":"Green and Gray"},{"time":"6:29","artist":"The Tony Rice Unit","title":"Old Gray Coat"},{"time":"6:23","artist":"Damien Rice with Lisa Hannigan","title":"Grey Room"},{"time":"6:16","artist":"Tannahill Weavers","title":"Hieland Harry"},{"time":"6:10","artist":"Kate Campbell","title":"Strangeness of the Day"},{"time":"6:06","artist":"Laurie Lewis and the Right Hands","title":"Bury Me In Bluegrass"},{"time":"6:02","artist":"Ali Farka Toure & Ry Cooder","title":"Bonde"}]