[{"time":"2:57","artist":"The Envy Corps","title":"Ms. Hospital Corners","id":216975},{"time":"2:52","artist":"The Twilight Singers","title":"Underneath the Waves","id":149387},{"time":"2:49","artist":"Zoo Animal","title":"Black and Charred","id":219561},{"time":"2:44","artist":"Edward Sharpe and The Magnetic Zeros","title":"Man On Fire","id":221297},{"time":"2:40","artist":"David Bowie","title":"Song For Bob Dylan","id":210245},{"time":"2:36","artist":"Ximena Sarinana","title":"Different","id":215495},{"time":"2:34","artist":"Howler","title":"Pythagorean Fearem","id":220881},{"time":"2:29","artist":"The Shins","title":"40 Mark Strasse","id":221272},{"time":"2:27","artist":"Bee Gees","title":"New York Mining Disaster 1941","id":196140},{"time":"2:22","artist":"Foo Fighters","title":"Walk","id":213346},{"time":"2:19","artist":"Yukon Blonde","title":"Stairway","id":220571},{"time":"2:14","artist":"Moon Maan","title":"Chain YR Soul","id":159517},{"time":"2:10","artist":"Metronomy","title":"The Look","id":216253},{"time":"2:06","artist":"Coldplay","title":"Viva La Vida","id":187984},{"time":"2:03","artist":"Perfume Genius","title":"Dark Parts","id":220549},{"time":"2:00","artist":"Bad Religion","title":"21st Century (Digital Boy)","id":139900}]