[{"time":"4:59","artist":"Paul Westerberg","title":"Love Untold","id":132538},{"time":"4:55","artist":"The Replacements","title":"I Will Dare","id":131743},{"time":"4:48","artist":"David Bowie","title":"Space Oddity","id":130732},{"time":"4:42","artist":"David Bowie","title":"I'm Afraid Of Americans","id":185228},{"time":"4:39","artist":"David Bowie","title":"Sound And Vision","id":202603},{"time":"4:34","artist":"Beck","title":"Girl","id":136092},{"time":"4:31","artist":"Beck","title":"The New Pollution","id":130424},{"time":"4:27","artist":"Beck","title":"Loser","id":204913},{"time":"4:13","artist":"The Clash","title":"Straight To Hell","id":134405},{"time":"4:10","artist":"The Clash","title":"Career Opportunities","id":131113},{"time":"4:08","artist":"The Clash","title":"I Fought The Law","id":131111},{"time":"4:02","artist":"Sheryl Crow","title":"If It Makes You Happy"}]