[{"time":"2:56","artist":"Night Moves","title":"Colored Emotions","id":228362},{"time":"2:49","artist":"Pete Yorn","title":"Last Summer","id":197614},{"time":"2:46","artist":"Low","title":"Plastic Cup","id":227980},{"time":"2:44","artist":"Wilco","title":"The Late Greats","id":133347},{"time":"2:40","artist":"Jose James","title":"Trouble","id":228486},{"time":"2:36","artist":"Family Of The Year","title":"Hero","id":226753},{"time":"2:34","artist":"The Clash","title":"Hateful","id":210182},{"time":"2:28","artist":"Creedence Clearwater Revival","title":"Keep On Chooglin'","id":200159},{"time":"2:22","artist":"Purity Ring","title":"Fineshrine","id":223664},{"time":"2:18","artist":"Django Django","title":"Default","id":224668},{"time":"2:14","artist":"The Chalice","title":"Push It","id":222080},{"time":"2:10","artist":"Nirvana","title":"Come as You Are","id":139998},{"time":"2:07","artist":"Local Natives","title":"Mt Washington","id":228568},{"time":"2:02","artist":"Alt-J","title":"Tessellate","id":223228}]