[{"time":"12:59","artist":"Dillinger Four","title":"Fire Side Chat","id":140638},{"time":"12:50","artist":"Parliament","title":"Flashlight","id":132416},{"time":"12:46","artist":"808 State","title":"Pacific State","id":134961},{"time":"12:42","artist":"Supreme Beings of Leisure","title":"Ghetto","id":132583},{"time":"12:34","artist":"Prince","title":"3121","id":147599},{"time":"12:31","artist":"Squeeze","title":"Is That Love","id":133115},{"time":"12:29","artist":"Joy Division","title":"Warsaw","id":132076},{"time":"12:20","artist":"Atmosphere","title":"Smart Went Crazy","id":141196},{"time":"12:15","artist":"Drive-By Truckers","title":"Easy On Yourself","id":146921},{"time":"12:12","artist":"Idlewild","title":"Mistake Pageant","id":136416}]