[{"time":"5:58","artist":"Massive Attack","title":"Protection","id":131437},{"time":"5:55","artist":"Sufjan Stevens","title":"Heirloom","id":207696},{"time":"5:51","artist":"Of Montreal","title":"Famine Affair","id":208122},{"time":"5:46","artist":"Beastie Boys","title":"Shadrach","id":134114},{"time":"5:41","artist":"Pink Mink","title":"Earthquake On The Loose","id":206965},{"time":"5:37","artist":"Terry Reid","title":"Speak Now Or Forever Hold Your Peace","id":140401},{"time":"5:34","artist":"Yeah Yeah Yeahs","title":"Gold Lion","id":145644},{"time":"5:28","artist":"Warpaint","title":"Undertow","id":208771},{"time":"5:24","artist":"Jimi Hendrix","title":"Fire","id":133810},{"time":"5:20","artist":"Spoon","title":"The Mystery Zone","id":203238},{"time":"5:15","artist":"Primal Scream","title":"Nitty Gritty","id":151485},{"time":"5:11","artist":"Matt and Kim","title":"Cameras","id":207721},{"time":"5:06","artist":"Rufus Wainwright","title":"Release The Stars","id":158293},{"time":"5:02","artist":"The Cribs","title":"Hey Scenesters!","id":140266}]