[{"time":"5:59","artist":"Joy Division","title":"Transmission","id":134889},{"time":"5:55","artist":"Django Django","title":"Hail Bop","id":224273},{"time":"5:52","artist":"Lorde","title":"Tennis Court","id":235932},{"time":"5:48","artist":"Eno / Hyde","title":"Daddy's Car","id":240173},{"time":"5:45","artist":"Sonny Knight and The Lakers","title":"Hey Girl","id":234301},{"time":"5:42","artist":"Run DMC","title":"Jam-Master Jay","id":180610},{"time":"5:37","artist":"The 4onthefloor","title":"Junkie","id":242213},{"time":"5:34","artist":"Howler","title":"Don't Wanna","id":238545},{"time":"5:30","artist":"The Black Keys","title":"Fever","id":240128},{"time":"5:27","artist":"Lee \"Scratch\" Perry","title":"Lee Perry Guiding Star Dub","id":210632},{"time":"5:23","artist":"Lissie","title":"Shameless","id":230716},{"time":"5:20","artist":"Bob Mould","title":"I Don't Know You Anymore","id":242209},{"time":"5:15","artist":"Benjamin Gibbard","title":"Bigger Than Love feat. Aimee Mann","id":225725},{"time":"5:12","artist":"Max Frost","title":"White Lies","id":238837},{"time":"5:09","artist":"Talking Heads","title":"Wild Wild Life","id":132286},{"time":"5:05","artist":"Sharon Van Etten","title":"Taking Chances","id":239689},{"time":"5:01","artist":"The White Stripes","title":"Seven Nation Army","id":131129}]