[{"time":"7:57","artist":"Sharon Van Etten","title":"Save Yourself","id":208515},{"time":"7:53","artist":"Toro Y Moi","title":"Still Sound","id":211021},{"time":"7:48","artist":"The Owls","title":"Peppermint Patty","id":179964},{"time":"7:44","artist":"TV On The Radio","title":"Will Do","id":211786},{"time":"7:41","artist":"Buffalo Springfield","title":"Expecting To Fly","id":148915},{"time":"7:37","artist":"My Morning Jacket","title":"Holdin On To Black Metal","id":213461},{"time":"7:32","artist":"Dr. Dog","title":"Shadow People","id":204683},{"time":"7:26","artist":"Zero 7","title":"Destiny","id":133252},{"time":"7:22","artist":"Soul Coughing","title":"True Dreams of Wichita","id":133703},{"time":"7:18","artist":"Kurt Vile","title":"Jesus Fever","id":212055},{"time":"7:14","artist":"Florence and the Machine","title":"You've Got The Love","id":211692},{"time":"7:10","artist":"Belle and Sebastian","title":"I Want The World To Stop","id":208509},{"time":"7:06","artist":"The Subways","title":"Mary","id":142335},{"time":"7:02","artist":"Foo Fighters","title":"Rope","id":211693}]